pyDeltafile/__init__.py
pyDeltafile/delta.py
tests/__init__.py
tests/test_delta.py
pydeltafile-1.1.0.dist-info/LICENSE
pydeltafile-1.1.0.dist-info/METADATA
pydeltafile-1.1.0.dist-info/WHEEL
pydeltafile-1.1.0.dist-info/top_level.txt
pydeltafile-1.1.0.dist-info/RECORD
