Metadata-Version: 2.2
Name: pyDeltafile
Version: 1.1.0
License-File: LICENSE
Requires-Dist: pandas
Dynamic: requires-dist
